sfrout/__init__.py
sfrout/main.py
sfrout/app/__init__.py
sfrout/app/cli.py
sfrout/components/__init__.py
sfrout/components/config.py
sfrout/components/connectors.py
sfrout/components/containers.py
sfrout/components/exceptions.py
sfrout/components/handlers.py
sfrout/components/loggers.py
sfrout-0.0.27.dist-info/METADATA
sfrout-0.0.27.dist-info/WHEEL
sfrout-0.0.27.dist-info/entry_points.txt
sfrout-0.0.27.dist-info/licenses/LICENSE.md
sfrout-0.0.27.dist-info/RECORD
