Metadata-Version: 2.1
Name: sfrout
Version: 0.0.27
Summary: Scalable, asynchronious SalesForce (SFDC) report downloader for SSO/SAML clients
Project-URL: Homepage, https://github.com/LukaszHoszowski/sfrout
Project-URL: Bug Tracker, https://github.com/LukaszHoszowski/sfrout/issues
Project-URL: Documentation, https://sfrout.readthedocs.io
Author-email: Lukasz Hoszowski <lukasz.hoszowski@mail.com>
License-File: LICENSE.md
Keywords: Report,SFDC,SalesForce
Classifier: Development Status :: 3 - Alpha
Classifier: Intended Audience :: End Users/Desktop
Classifier: License :: OSI Approved :: Apache Software License
Classifier: Operating System :: Microsoft :: Windows :: Windows 10
Classifier: Programming Language :: Python :: 3.11
Requires-Python: >=3.11
Requires-Dist: aiodns<4,>=3.0.0
Requires-Dist: aiohttp<4,>=3.8.4
Requires-Dist: asyncio<4,>=3.4.3
Requires-Dist: browser-cookie3<1,>=0.17.0
Requires-Dist: click<9,>=8.1.3
Requires-Dist: pandas<2,>=1.5.3
Requires-Dist: requests<3,>=2.28.2
Requires-Dist: tabulate<1,>=0.9.0
Requires-Dist: tqdm<5,>=4.64.1
